clearbox_wrapper/__init__.py
clearbox_wrapper/data_preparation/__init__.py
clearbox_wrapper/data_preparation/data_preparation.py
clearbox_wrapper/exceptions/__init__.py
clearbox_wrapper/exceptions/exceptions.py
clearbox_wrapper/keras/__init__.py
clearbox_wrapper/keras/keras.py
clearbox_wrapper/model/__init__.py
clearbox_wrapper/model/model.py
clearbox_wrapper/preprocessing/__init__.py
clearbox_wrapper/preprocessing/preprocessing.py
clearbox_wrapper/pyfunc/__init__.py
clearbox_wrapper/pyfunc/model.py
clearbox_wrapper/pyfunc/pyfunc.py
clearbox_wrapper/pytorch/__init__.py
clearbox_wrapper/pytorch/pickle_module.py
clearbox_wrapper/pytorch/pytorch.py
clearbox_wrapper/schema/__init__.py
clearbox_wrapper/schema/schema.py
clearbox_wrapper/schema/utils.py
clearbox_wrapper/signature/__init__.py
clearbox_wrapper/signature/signature.py
clearbox_wrapper/sklearn/__init__.py
clearbox_wrapper/sklearn/sklearn.py
clearbox_wrapper/utils/__init__.py
clearbox_wrapper/utils/environment.py
clearbox_wrapper/utils/file_utils.py
clearbox_wrapper/utils/model_utils.py
clearbox_wrapper/wrapper/__init__.py
clearbox_wrapper/wrapper/model.py
clearbox_wrapper/wrapper/utils.py
clearbox_wrapper/wrapper/wrapper.py
clearbox_wrapper/xgboost/__init__.py
clearbox_wrapper/xgboost/xgboost.py
clearbox_wrapper-0.3.11.dist-info/LICENSE
clearbox_wrapper-0.3.11.dist-info/WHEEL
clearbox_wrapper-0.3.11.dist-info/METADATA
clearbox_wrapper-0.3.11.dist-info/RECORD
