Metadata-Version: 2.1
Name: clearbox-wrapper
Version: 0.3.11
Summary: An agnostic wrapper for the most common frameworks of ML models.
Home-page: https://clearbox.ai
License: Apache-2.0
Keywords: ML wrapper,machine learning
Author: Clearbox AI
Author-email: info@clearbox.ai
Requires-Python: >=3.6.2,<4.0.0
Classifier: License :: OSI Approved :: Apache Software License
Classifier: Programming Language :: Python :: 3
Classifier: Programming Language :: Python :: 3.7
Classifier: Programming Language :: Python :: 3.8
Classifier: Programming Language :: Python :: 3.9
Requires-Dist: PyYAML (>=5.4.1,<6.0.0)
Requires-Dist: cloudpickle (>=1.6.0,<2.0.0)
Requires-Dist: loguru (>=0.5.3,<0.6.0)
Requires-Dist: numpy (>=1.16.0,<2.0.0)
Requires-Dist: pandas (>=1,<2)
Project-URL: Repository, https://github.com/ClearBox-AI/clearbox-wrapper
